bayes_traj/__init__.py
bayes_traj/bayes_traj_main.py
bayes_traj/bayes_traj_refiner.py
bayes_traj/fit_stats.py
bayes_traj/generate_generic_data.py
bayes_traj/generate_prior.py
bayes_traj/get_constraints_graph.py
bayes_traj/get_longitudinal_constraints_graph.py
bayes_traj/mult_dp_regression.py
bayes_traj/prior_from_model.py
bayes_traj/psis.py
bayes_traj/summarize_traj_model.py
bayes_traj/utils.py
bayes_traj/viz_data_prior_draws.py
bayes_traj/viz_gamma_dists.py
bayes_traj/viz_model_trajs.py
bayes_traj/tests/__init__.py
bayes_traj/tests/test_fit_stats.py
bayes_traj/tests/test_mult_dp_regression.py
bayes_traj/tests/test_utils.py
bayes_traj-0.1.5.dist-info/METADATA
bayes_traj-0.1.5.dist-info/WHEEL
bayes_traj-0.1.5.dist-info/entry_points.txt
bayes_traj-0.1.5.dist-info/top_level.txt
bayes_traj-0.1.5.dist-info/RECORD
